gensh/__init__.py
gensh/processor.py
gensh/templates/__init__.py
gensh/templates/analyze-logs.yml
gensh/templates/architect.yml
gensh/templates/book-summary.yml
gensh/templates/code-python.yml
gensh/templates/code-shell.yml
gensh/templates/links-summary.yml
gensh/templates/pm-news.yml
gensh/templates/security-news.yml
gensh-0.8.11.dist-info/METADATA
gensh-0.8.11.dist-info/WHEEL
gensh-0.8.11.dist-info/entry_points.txt
gensh-0.8.11.dist-info/RECORD
