Metadata-Version: 2.4
Name: gensh
Version: 0.8.11
Summary: GenSh - Generate and execute code using natural language
Author-email: Vaibhav Bhandari <vaibhavb@gmail.com>
License: MIT
Requires-Python: <4.0,>=3.12
Requires-Dist: beautifulsoup4<5.0.0,>=4.9.3
Requires-Dist: markdown<4.0.0,>=3.3.0
Requires-Dist: openai<2.0.0,>=1.0.0
Requires-Dist: python-dotenv<1.0.0,>=0.19.0
Requires-Dist: pyyaml<7.0,>=6.0
Requires-Dist: requests<3.0.0,>=2.25.0
